wendyhielolib/__init__.py
wendyhielolib/mod.py
wendyhielolib-0.0.1.dist-info/METADATA
wendyhielolib-0.0.1.dist-info/WHEEL
wendyhielolib-0.0.1.dist-info/RECORD
